ratesetterClient-0.2.3.dist-info/DESCRIPTION.rst
ratesetterClient-0.2.3.dist-info/METADATA
ratesetterClient-0.2.3.dist-info/RECORD
ratesetterClient-0.2.3.dist-info/WHEEL
ratesetterClient-0.2.3.dist-info/metadata.json
ratesetterClient-0.2.3.dist-info/top_level.txt
ratesetterclient/__init__.py
ratesetterclient/api.py
ratesetterclient/log.py
