Metadata-Version: 2.0
Name: ratesetterClient
Version: 0.2.3
Summary: python library for ratesetter.com
Home-page: https://github.com/jfparis/ratesetterClient
Author: Jean-Francois Paris
Author-email: jfparis@rouge.eu.org
License: LGPL 2.0
Platform: UNKNOWN
Classifier: Development Status :: 5 - Production/Stable
Classifier: Intended Audience :: Developers
Classifier: Natural Language :: English
Classifier: License :: OSI Approved :: GNU Lesser General Public License v3 or later (LGPLv3+)
Classifier: Programming Language :: Python
Classifier: Programming Language :: Python :: 2.7
Classifier: Programming Language :: Python :: 3
Requires-Dist: lxml
Requires-Dist: pandas
Requires-Dist: requests
